LICENSE
MANIFEST.in
README.rst
setup.py
aio_space_track_api/__init__.py
aio_space_track_api/client.py
aio_space_track_api/log.py
aio_space_track_api/utils.py
aio_space_track_api.egg-info/PKG-INFO
aio_space_track_api.egg-info/SOURCES.txt
aio_space_track_api.egg-info/dependency_links.txt
aio_space_track_api.egg-info/requires.txt
aio_space_track_api.egg-info/top_level.txt
aio_space_track_api/__pycache__/__init__.cpython-36.pyc
aio_space_track_api/__pycache__/client.cpython-36.pyc
aio_space_track_api/__pycache__/log.cpython-36.pyc
examples/server.py
examples/simple.py