Metadata-Version: 1.1
Name: aio-space-track-api
Version: 2.1.1
Summary: Small async wrapper for "space-track-api" package.
Home-page: https://github.com/nkoshell/aio-space-track-api
Author: NikitaKoshelev
Author-email: nikita.koshelev@gmail.com
License: MIT
Download-URL: https://github.com/nkoshell/aio-space-track-api/archive/2.1.1.tar.gz
Platform: UNKNOWN
